mapper/__init__.py
mapper/casedict.py
mapper/object_mapper.py
mapper/object_mapper_exception.py
tests/__init__.py
tests/test_object_mapper.py
object_mapper_coop-0.0.1.dist-info/LICENSE
object_mapper_coop-0.0.1.dist-info/LICENSE.txt
object_mapper_coop-0.0.1.dist-info/METADATA
object_mapper_coop-0.0.1.dist-info/WHEEL
object_mapper_coop-0.0.1.dist-info/top_level.txt
object_mapper_coop-0.0.1.dist-info/RECORD
