Metadata-Version: 2.1
Name: object-mapper-coop
Version: 0.0.1
Summary: ObjectMapper is a class for automatic object mapping. It helps you to create objects between                project layers (data layer, service layer, view) in a simple, transparent way.
Home-page: https://github.com/tylertjburns/object-mapper
Author: tburns
Author-email: tyler.tj.burns@gmail.com
License: MIT
Requires-Dist: datetime
Requires-Dist: nose
Provides-Extra: dev
Provides-Extra: test
Requires-Dist: nose ; extra == 'test'
